{
    "status": "SUCCESS",
    "data": {
        "device_id": "test",
            "books": [
                {
                    "name": "Video01",
                    "thumbnail_url": "https://raw.githubusercontent.com/AmanBohra7/VR360VideoPlayer/main/Images/video_01_thumbnail.jpg"
                },
                {
                    "name": "Video02",
                    "thumbnail_url": "https://raw.githubusercontent.com/AmanBohra7/VR360VideoPlayer/main/Images/video_02_thumbnail.jpg"
                },
                {
                    "name": "Video03",
                    "thumbnail_url": "https://raw.githubusercontent.com/AmanBohra7/VR360VideoPlayer/main/Images/video_03_thumbnail.jpg"
                },
                {
                    "name": "Video04",
                    "thumbnail_url": "https://raw.githubusercontent.com/AmanBohra7/VR360VideoPlayer/main/Images/video_04_thumbnail.jpg"
                }

            ]
    }
}